WebDialogs/__init__.py
WebDialogs/client/__init__.py
WebDialogs/client/backend_controller.py
WebDialogs/client/webdialogs_keywords.py
WebDialogs/server/__init__.py
WebDialogs/server/app.py
WebDialogs/server/run.py
WebDialogs/server/blueprints/__init__.py
WebDialogs/server/blueprints/api.py
WebDialogs/server/blueprints/dialog.py
WebDialogs/server/services/__init__.py
WebDialogs/server/services/test_manager.py
WebDialogs/server/services/utils.py
WebDialogs/server/services/dialogs/__init__.py
WebDialogs/server/services/dialogs/base.py
WebDialogs/server/services/dialogs/builder.py
WebDialogs/server/services/dialogs/manager.py
WebDialogs/server/templates/home.html
WebDialogs/server/templates/layout.html
WebDialogs/server/templates/dialogs/dialog_execute_manual_step.html
WebDialogs/server/templates/dialogs/dialog_get_selection_from_user.html
WebDialogs/server/templates/dialogs/dialog_get_selections_from_user.html
WebDialogs/server/templates/dialogs/dialog_get_value_from_user.html
WebDialogs/server/templates/dialogs/dialog_pause_execution.html
WebDialogs/server/templates/dialogs/layout.html
robotframework_webdialogs-0.1.1.dist-info/LICENSE
robotframework_webdialogs-0.1.1.dist-info/METADATA
robotframework_webdialogs-0.1.1.dist-info/WHEEL
robotframework_webdialogs-0.1.1.dist-info/top_level.txt
robotframework_webdialogs-0.1.1.dist-info/RECORD
