Metadata-Version: 2.1
Name: robotframework-webdialogs
Version: 0.1.1
Summary: k
Home-page: https://github.com/Ymil/robotframework-webdialogs
Author: Lautaro Linquimán
Author-email: lylinquiman@gmail.com
License: Apache License 2.0
Platform: any
Classifier: License :: OSI Approved :: Apache Software License
Classifier: Operating System :: OS Independent
Classifier: Programming Language :: Python
Classifier: Programming Language :: Python :: 3.11
Classifier: Programming Language :: Python :: 3.12
Classifier: Programming Language :: Python :: 3.13
Classifier: Programming Language :: Python :: 3 :: Only
Classifier: Topic :: Software Development :: Testing
Classifier: Framework :: Robot Framework
Classifier: Framework :: Robot Framework :: Library
Requires-Python: >=3.8, <3.14
License-File: LICENSE
Requires-Dist: flask
Requires-Dist: robotframework
Requires-Dist: requests
